lenskit_implicit/__init__.py
lenskit_implicit/_pt.py
lenskit_implicit/implicit.py
lenskit_implicit-0.14.0.dist-info/LICENSE.md
lenskit_implicit-0.14.0.dist-info/WHEEL
lenskit_implicit-0.14.0.dist-info/METADATA
lenskit_implicit-0.14.0.dist-info/RECORD
